pymsbuild_msix/_version.py
pymsbuild_msix/_build.py
pymsbuild_msix/_types.py
pymsbuild_msix/__init__.py
pymsbuild_msix-0.1.0a2.dist-info/METADATA
pymsbuild_msix-0.1.0a2.dist-info/entry_points.txt
pymsbuild_msix-0.1.0a2.dist-info/WHEEL
pymsbuild_msix-0.1.0a2.dist-info/RECORD