Metadata-Version: 2.2
Name: pymsbuild-msix
Version: 0.1.0a2
Author: Steve Dower
Author-email: steve.dower@python.org
Project-url: Homepage, https://github.com/zooba/pymsbuild-msix
Project-url: Report bug, https://github.com/zooba/pymsbuild-msix/issues
Summary: A pymsbuild extension for producing MSIX packages.
Keywords: build,pep-517,msbuild,packaging,msix,Windows
Classifier: Development Status :: 3 - Alpha
Classifier: Intended Audience :: Developers
Classifier: License :: OSI Approved :: MIT License
Classifier: Operating System :: Microsoft :: Windows
Classifier: Programming Language :: Python :: 3.10
Classifier: Programming Language :: Python :: 3.11
Classifier: Programming Language :: Python :: 3.12
Classifier: Programming Language :: Python :: 3.13
Classifier: Programming Language :: Python :: 3.14
Classifier: Topic :: Software Development :: Build Tools
Classifier: Topic :: Software Development :: Compilers
Classifier: Topic :: Utilities
Requires-Dist: pymsbuild>=1.2.2a1
Requires-Dist: entrypoints
